MANIFEST.in
README.md
setup.cfg
setup.py
dcron/__init__.py
dcron/application.py
dcron/processor.py
dcron/scheduler.py
dcron/site.py
dcron/storage.py
dcron/utils.py
dcron.egg-info/PKG-INFO
dcron.egg-info/SOURCES.txt
dcron.egg-info/dependency_links.txt
dcron.egg-info/entry_points.txt
dcron.egg-info/requires.txt
dcron.egg-info/top_level.txt
dcron/cron/__init__.py
dcron/cron/cronitem.py
dcron/cron/crontab.py
dcron/cron/crontabs.py
dcron/cron/orderedvariablelist.py
dcron/cron/utils.py
dcron/datagram/__init__.py
dcron/datagram/client.py
dcron/datagram/server.py
dcron/protocols/__init__.py
dcron/protocols/messages.py
dcron/protocols/packet.py
dcron/protocols/udpserializer.py
dcron/static/css/site.css
dcron/static/js/jquery-3.3.1.min.js
dcron/templates/base.html
dcron/templates/index.html
dcron/templates/joblogs.html
dcron/templates/jobstable.html
dcron/templates/nodestable.html